[
  {
    "name": "review_status",
    "description": "Check the current Monocle review status. Returns whether feedback is pending, a pause was requested, or no feedback is available."
  },
  {
    "name": "get_feedback",
    "description": "Retrieve review feedback from Monocle. With wait=true, blocks until the reviewer submits feedback."
  },
  {
    "name": "send_artifact",
    "description": "Send content to Monocle for the reviewer to see. Provide content directly or pass file_path to read from disk."
  },
  {
    "name": "add_files",
    "description": "Add file paths to the current Monocle review session."
  },
  {
    "name": "remove_files",
    "description": "Remove previously-added file paths from the current Monocle review session. Pass the same paths used with add_files."
  }
]
